ganesha_experimental/__init__.py
ganesha_experimental/main.py
ganesha_experimental-5.0.0.dist-info/LICENSE
ganesha_experimental-5.0.0.dist-info/METADATA
ganesha_experimental-5.0.0.dist-info/WHEEL
ganesha_experimental-5.0.0.dist-info/top_level.txt
ganesha_experimental-5.0.0.dist-info/RECORD
