Metadata-Version: 2.1
Name: ganesha-experimental
Version: 5.0.0
Summary: A small package experiment
Home-page: https://gitlab.com/awakzdev/python-app
Author: Elazar Chodjayev
Author-email: zenmyx@gmail.com
License: UNKNOWN
Platform: UNKNOWN
Classifier: Programming Language :: Python :: 3
Classifier: License :: OSI Approved :: MIT License
Classifier: Operating System :: OS Independent
Requires-Python: >=3.7
